conda_subprocess/__init__.py
conda_subprocess/_version.py
conda_subprocess/decorator.py
conda_subprocess/interface.py
conda_subprocess/process.py
conda_subprocess-0.0.10.dist-info/METADATA
conda_subprocess-0.0.10.dist-info/WHEEL
conda_subprocess-0.0.10.dist-info/licenses/LICENSE
conda_subprocess-0.0.10.dist-info/RECORD
