Metadata-Version: 2.4
Name: conda_subprocess
Version: 0.0.10
Summary: Run a subprocess in a different conda environment.
Project-URL: Repository, https://github.com/pyiron/conda_subprocess
Author-email: Jan Janssen <janssen@mpie.de>
License: BSD 3-Clause License
License-File: LICENSE
Keywords: conda,subprocess
Classifier: Development Status :: 5 - Production/Stable
Classifier: Intended Audience :: Science/Research
Classifier: License :: OSI Approved :: BSD License
Classifier: Operating System :: OS Independent
Classifier: Programming Language :: Python :: 3.9
Classifier: Programming Language :: Python :: 3.10
Classifier: Programming Language :: Python :: 3.11
Classifier: Programming Language :: Python :: 3.12
Classifier: Programming Language :: Python :: 3.13
Classifier: Topic :: Utilities
Requires-Python: >=3.9
Requires-Dist: conda<=25.9.1,>=22.9.0
Provides-Extra: executorlib
Requires-Dist: executorlib==1.7.1; extra == 'executorlib'
